{"doy": "Day_year", "month": "Month", "pressure_mousehole_1": "('mousehole', 'pressure_1')", "pressure_mousehole_2": "('mousehole', 'pressure_2')", "pressure_mousehole_3": "('mousehole', 'pressure_3')", "pressure_mousehole_4": "('mousehole', 'pressure_4')", "pressure_mousehole_5": "('mousehole', 'pressure_5')", "pressure_staplegrove_1": "('staplegrove', 'pressure_1')", "pressure_staplegrove_2": "('staplegrove', 'pressure_2')", "pressure_staplegrove_3": "('staplegrove', 'pressure_3')", "pressure_staplegrove_4": "('staplegrove', 'pressure_4')", "pressure_staplegrove_5": "('staplegrove', 'pressure_5')", "solar_irradiance_mousehole_1": "('mousehole', 'solar_irradiance_1')", "solar_irradiance_mousehole_1_lag_1": "('mousehole', 'solar_irradiance_1_lag_1')", "solar_irradiance_mousehole_1_lag_2": "('mousehole', 'solar_irradiance_1_lag_2')", "solar_irradiance_mousehole_2_lag_1": "('mousehole', 'solar_irradiance_2_lag_1')", "solar_irradiance_mousehole_2_lag_2": "('mousehole', 'solar_irradiance_2_lag_2')", "solar_irradiance_mousehole_3_lag_1": "('mousehole', 'solar_irradiance_3_lag_1')", "solar_irradiance_mousehole_3_lag_2": "('mousehole', 'solar_irradiance_3_lag_2')", "solar_irradiance_mousehole_4": "('mousehole', 'solar_irradiance_4')", "solar_irradiance_mousehole_4_lag_1": "('mousehole', 'solar_irradiance_4_lag_1')", "solar_irradiance_mousehole_4_lag_2": "('mousehole', 'solar_irradiance_4_lag_2')", "solar_irradiance_mousehole_5": "('mousehole', 'solar_irradiance_5')", "solar_irradiance_mousehole_5_lag_1": "('mousehole', 'solar_irradiance_5_lag_1')", "solar_irradiance_mousehole_5_lag_2": "('mousehole', 'solar_irradiance_5_lag_2')", "solar_irradiance_mousehole_mean": "('mousehole', 'solar_mean')", "solar_irradiance_mousehole_range": "('mousehole', 'solar_range')", "solar_irradiance_staplegrove_1": "('staplegrove', 'solar_irradiance_1')", "solar_irradiance_staplegrove_1_lag_1": "('staplegrove', 'solar_irradiance_1_lag_1')", "solar_irradiance_staplegrove_1_lag_2": "('staplegrove', 'solar_irradiance_1_lag_2')", "solar_irradiance_staplegrove_2_lag_1": "('staplegrove', 'solar_irradiance_2_lag_1')", "solar_irradiance_staplegrove_2_lag_2": "('staplegrove', 'solar_irradiance_2_lag_2')", "solar_irradiance_staplegrove_3": "('staplegrove', 'solar_irradiance_3')", "solar_irradiance_staplegrove_3_lag_1": "('staplegrove', 'solar_irradiance_3_lag_1')", "solar_irradiance_staplegrove_3_lag_2": "('staplegrove', 'solar_irradiance_3_lag_2')", "solar_irradiance_staplegrove_4": "('staplegrove', 'solar_irradiance_4')", "solar_irradiance_staplegrove_4_lag_1": "('staplegrove', 'solar_irradiance_4_lag_1')", "solar_irradiance_staplegrove_4_lag_2": "('staplegrove', 'solar_irradiance_4_lag_2')", "solar_irradiance_staplegrove_5_lag_1": "('staplegrove', 'solar_irradiance_5_lag_1')", "solar_irradiance_staplegrove_5_lag_2": "('staplegrove', 'solar_irradiance_5_lag_2')", "solar_irradiance_staplegrove_mean": "('staplegrove', 'solar_mean')", "solar_irradiance_staplegrove_range": "('staplegrove', 'solar_range')", "spec_humidity_mousehole_1": "('mousehole', 'spec_humidity_1')", "spec_humidity_mousehole_2": "('mousehole', 'spec_humidity_2')", "spec_humidity_mousehole_3": "('mousehole', 'spec_humidity_3')", "spec_humidity_mousehole_4": "('mousehole', 'spec_humidity_4')", "spec_humidity_mousehole_5": "('mousehole', 'spec_humidity_5')", "spec_humidity_staplegrove_1": "('staplegrove', 'spec_humidity_1')", "spec_humidity_staplegrove_2": "('staplegrove', 'spec_humidity_2')", "spec_humidity_staplegrove_3": "('staplegrove', 'spec_humidity_3')", "spec_humidity_staplegrove_4": "('staplegrove', 'spec_humidity_4')", "spec_humidity_staplegrove_5": "('staplegrove', 'spec_humidity_5')", "speed_mousehole_2": "('mousehole', 'speed_2')", "speed_mousehole_3": "('mousehole', 'speed_3')", "speed_mousehole_4": "('mousehole', 'speed_4')", "speed_mousehole_5": "('mousehole', 'speed_5')", "speed_staplegrove_1": "('staplegrove', 'speed_1')", "speed_staplegrove_2": "('staplegrove', 'speed_2')", "speed_staplegrove_3": "('staplegrove', 'speed_3')", "speed_staplegrove_4": "('staplegrove', 'speed_4')", "speed_staplegrove_5": "('staplegrove', 'speed_5')", "temperature_mousehole_1": "('mousehole', 'temperature_1')", "temperature_mousehole_1_lag_1": "('mousehole', 'temperature_1_lag_1')", "temperature_mousehole_1_lag_2": "('mousehole', 'temperature_1_lag_2')", "temperature_mousehole_2": "('mousehole', 'temperature_2')", "temperature_mousehole_2_lag_1": "('mousehole', 'temperature_2_lag_1')", "temperature_mousehole_2_lag_2": "('mousehole', 'temperature_2_lag_2')", "temperature_mousehole_3": "('mousehole', 'temperature_3')", "temperature_mousehole_3_lag_1": "('mousehole', 'temperature_3_lag_1')", "temperature_mousehole_3_lag_2": "('mousehole', 'temperature_3_lag_2')", "temperature_mousehole_4": "('mousehole', 'temperature_4')", "temperature_mousehole_4_lag_1": "('mousehole', 'temperature_4_lag_1')", "temperature_mousehole_4_lag_2": "('mousehole', 'temperature_4_lag_2')", "temperature_mousehole_5": "('mousehole', 'temperature_5')", "temperature_mousehole_5_lag_1": "('mousehole', 'temperature_5_lag_1')", "temperature_mousehole_5_lag_2": "('mousehole', 'temperature_5_lag_2')", "temperature_staplegrove_1": "('staplegrove', 'temperature_1')", "temperature_staplegrove_1_lag_1": "('staplegrove', 'temperature_1_lag_1')", "temperature_staplegrove_1_lag_2": "('staplegrove', 'temperature_1_lag_2')", "temperature_staplegrove_2": "('staplegrove', 'temperature_2')", "temperature_staplegrove_2_lag_1": "('staplegrove', 'temperature_2_lag_1')", "temperature_staplegrove_2_lag_2": "('staplegrove', 'temperature_2_lag_2')", "temperature_staplegrove_3": "('staplegrove', 'temperature_3')", "temperature_staplegrove_3_lag_1": "('staplegrove', 'temperature_3_lag_1')", "temperature_staplegrove_3_lag_2": "('staplegrove', 'temperature_3_lag_2')", "temperature_staplegrove_4": "('staplegrove', 'temperature_4')", "temperature_staplegrove_4_lag_1": "('staplegrove', 'temperature_4_lag_1')", "temperature_staplegrove_4_lag_2": "('staplegrove', 'temperature_4_lag_2')", "temperature_staplegrove_5": "('staplegrove', 'temperature_5')", "temperature_staplegrove_5_lag_1": "('staplegrove', 'temperature_5_lag_1')", "temperature_staplegrove_5_lag_2": "('staplegrove', 'temperature_5_lag_2')", "value_lag_96": "val_lag_96", "weekday": "Day", "weekend": "Minute", "solar_irradiance_mousehole_2": "('mousehole', 'solar_irradiance_2')", "solar_irradiance_mousehole_3": "('mousehole', 'solar_irradiance_3')", "solar_irradiance_staplegrove_2": "('staplegrove', 'solar_irradiance_2')", "solar_irradiance_staplegrove_5": "('staplegrove', 'solar_irradiance_5')", "solar_irradiance_staplegrove_max": "('staplegrove', 'solar_max')", "solar_irradiance_staplegrove_min": "('staplegrove', 'solar_min')", "solar_irradiance_mousehole_max": "('mousehole', 'solar_max')", "solar_irradiance_mousehole_min": "('mousehole', 'solar_min')", "value_diff_1": "val_grad", "value_diff_2": "val_grad_2", "value_diff_3": "val_grad_3", "solar_irradiance_mousehole_max___diff": "('mousehole', 'solar_max_grad')", "solar_irradiance_mousehole_max___ewm__alpha_0.9__mean": "('mousehole', 'solar_max_roll')", "solar_irradiance_mousehole_min___diff": "('mousehole', 'solar_min_grad')", "solar_irradiance_mousehole_min___ewm__alpha_0.9__mean": "('mousehole', 'solar_min_roll')", "solar_irradiance_staplegrove_max___diff": "('staplegrove', 'solar_max_grad')", "solar_irradiance_staplegrove_max___ewm__alpha_0.9__mean": "('staplegrove', 'solar_max_roll')", "solar_irradiance_staplegrove_min___diff": "('staplegrove', 'solar_min_grad')", "solar_irradiance_staplegrove_min___ewm__alpha_0.9__mean": "('staplegrove', 'solar_min_roll')", "value": "value", "hour": "Hour", "value___ewm__alpha_0.01__mean": "value_roll_mean_slow", "value___ewm__alpha_0.9__mean": "value_roll_mean_fast", "value___ewm__alpha_0.9__std": "value_roll_std", "value___rolling__window_12__max": "value_roll_max", "value___rolling__window_24__min": "value_roll_min", "solar_irradiance_mousehole_mean___diff": "('mousehole', 'solar_mean_grad')", "solar_irradiance_mousehole_mean___ewm__alpha_0.9__mean": "('mousehole', 'solar_mean_roll')", "solar_irradiance_staplegrove_mean___diff": "('staplegrove', 'solar_mean_grad')", "solar_irradiance_staplegrove_mean___ewm__alpha_0.9__mean": "('staplegrove', 'solar_mean_roll')", "value_lag_1": "val_lag_1", "value_lag_2": "val_lag_2", "value_lag_3": "val_lag_3", "value_lag_4": "val_lag_4", "value_lag_5": "val_lag_5", "value_lag_6": "val_lag_6", "value_lag_48": "val_lag_48", "value_lag_336": "val_lag_336", "demand_pc1": "PC1", "demand_pc2": "PC2", "demand_pc3": "PC3", "demand_pc4": "PC4", "demand_pc5": "PC5", "demand_pc6": "PC6", "demand_pc7": "PC7", "demand_pc8": "PC8", "demand_pc9": "PC9", "demand_pc10": "PC10", "demand_pc11": "PC11", "demand_pc12": "PC12", "demand_pc13": "PC13", "demand_pc14": "PC14", "demand_pc15": "PC15", "demand_pc16": "PC16", "demand_pc17": "PC17", "demand_pc18": "PC18", "demand_pc19": "PC19", "demand_pc20": "PC20", "direction_staplegrove_1": "('staplegrove', 'direction_1')", "direction_staplegrove_2": "('staplegrove', 'direction_2')", "direction_staplegrove_3": "('staplegrove', 'direction_3')", "direction_staplegrove_4": "('staplegrove', 'direction_4')", "direction_staplegrove_5": "('staplegrove', 'direction_5')", "direction_mousehole_1": "('mousehole', 'direction_1')", "speed_mousehole_1": "('mousehole', 'speed_1')", "direction_mousehole_2": "('mousehole', 'direction_2')", "direction_mousehole_3": "('mousehole', 'direction_3')", "direction_mousehole_4": "('mousehole', 'direction_4')", "direction_mousehole_5": "('mousehole', 'direction_5')"}